dlvm/__init__.py
dlvm/api_server/__init__.py
dlvm/api_server/dlv.py
dlvm/api_server/dpv.py
dlvm/api_server/dvg.py
dlvm/api_server/root.py
dlvm/common/__init__.py
dlvm/common/configure.py
dlvm/common/constant.py
dlvm/common/database.py
dlvm/common/default.cfg
dlvm/common/error.py
dlvm/common/loginit.py
dlvm/common/marshmallow_ext.py
dlvm/common/modules.py
dlvm/common/schema.py
dlvm/common/thin_mapping_template.xml
dlvm/common/utils.py
dlvm/dpv_agent/__init__.py
dlvm/dpv_agent/mirror_meta.py
dlvm/ihost_agent/__init__.py
dlvm/worker/__init__.py
dlvm/worker/allocator.py
dlvm/worker/dlv.py
dlvm/worker/dpv_handler_task.py
dlvm/worker/helper.py
dlvm/worker/lock_handler_task.py
dlvm/worker/monitor_ctx.py
dlvm/wrapper/__init__.py
dlvm/wrapper/action_check.py
dlvm/wrapper/api_wrapper.py
dlvm/wrapper/cmd_wrapper.py
dlvm/wrapper/command.py
dlvm/wrapper/hook.py
dlvm/wrapper/local_ctx.py
dlvm/wrapper/log_hook.py
dlvm/wrapper/mq_wrapper.py
dlvm/wrapper/rpc_lock.py
dlvm/wrapper/rpc_wrapper.py
dlvm/wrapper/state_machine.py
dlvm-0.5.0.data/data/bin/dlvm_bin/dm_dd
dlvm-0.5.0.data/data/bin/dlvm_bin/pdata_tools
dlvm-0.5.0.dist-info/METADATA
dlvm-0.5.0.dist-info/RECORD
dlvm-0.5.0.dist-info/WHEEL
dlvm-0.5.0.dist-info/entry_points.txt
dlvm-0.5.0.dist-info/top_level.txt
